convert_youtube_ttml_to_srt/__init__.py
convert_youtube_ttml_to_srt/convert_subtitle_ttml_to_srt.py
convert_youtube_ttml_to_srt-1.0.0.dist-info/LICENSE
convert_youtube_ttml_to_srt-1.0.0.dist-info/METADATA
convert_youtube_ttml_to_srt-1.0.0.dist-info/WHEEL
convert_youtube_ttml_to_srt-1.0.0.dist-info/top_level.txt
convert_youtube_ttml_to_srt-1.0.0.dist-info/RECORD
