Metadata-Version: 2.1
Name: convert-youtube-ttml-to-srt
Version: 1.0.0
Summary: convert youtube's ttml subtitle to rst format
Home-page: https://github.com/leftatrium2/convert_youtube_ttml_to_srt
Author: leftatrium
Author-email: leftatrium2@gmail.com
Classifier: Programming Language :: Python :: 3
Classifier: License :: OSI Approved :: MIT License
Classifier: Operating System :: OS Independent
License-File: LICENSE
